aleutian_client/__init__.py
aleutian_client/client.py
aleutian_client/exceptions.py
aleutian_client/models.py
aleutian_client-0.3.0.dist-info/licenses/LICENSE.txt
aleutian_client-0.3.0.dist-info/METADATA
aleutian_client-0.3.0.dist-info/WHEEL
aleutian_client-0.3.0.dist-info/top_level.txt
aleutian_client-0.3.0.dist-info/RECORD
