Metadata-Version: 2.4
Name: aleutian-client
Version: 0.3.0
Summary: The official Python client SDK for the AleutianLocal MLOps platform.
Author-email: John <support@aleutian.ai>
License:                     GNU AFFERO GENERAL PUBLIC LICENSE
Project-URL: Homepage, https://github.com/jinterlante1206/aleutian-client-python
Project-URL: Bug Tracker, https://github.com/jinterlante1206/aleutian-client-python/issues
Keywords: aleutian,mlops,local-ai
Classifier: Programming Language :: Python :: 3
Classifier: License :: OSI Approved :: GNU Affero General Public License v3 or later (AGPLv3+)
Classifier: Operating System :: OS Independent
Classifier: Topic :: Software Development :: Libraries :: Python Modules
Classifier: Topic :: Scientific/Engineering :: Artificial Intelligence
Requires-Python: >=3.9
License-File: LICENSE.txt
Requires-Dist: httpx>=0.25.0
Requires-Dist: pydantic>=2.0
Dynamic: license-file
